{"[hello?]":[38],"[i’m":[38],"[chapter":[340],"[this":[423,485,746,2100],"[we":[485],"[":[494,495,1353,2049,3506],"[while":[495],"[half":[495],"[i":[495,1548,2788],"[blinding":[729],"[here":[746],"[if":[813],"[you":[821,2792],"[and":[962],"[as":[1148,1149,1150,1151,1152,1153,1154,1155,1156],"[highly":[1485],"[whatever":[1485],"[fundamental":[1485],"[the":[1548,2793,3475],"[they":[1548,2177,2788],"[take":[1548],"[feel":[1548],"[turned":[2426],"[belle":[2552],"[je":[2552],"[thank":[2637],"[free":[2767],"[every":[2768],"[is":[2787],"[xxx]":[2787],"[one":[2790],"[all":[2792],"[bail":[2792],"[god":[3074],"[that’s":[3074],"[move!":[3476],"[how":[3506],"[what’s":[3560]}