{"「ろくでなし」":[127],"「みんなー":[1692],"「あたいみたいな天才目指して、頑張っていってね」":[1692],"「ちょっ、ちがっ、ばかじゃないもん」":[1692],"「ばかって言う方がばかなのよ」":[1692],"「なにようるさいわね、このばか！」":[1692],"「だから、ばかじゃないって言ってるでしょ」":[1692],"「いい加減にしないと冷凍するわよ」":[1692],"「そして粉々になって死ねばいいのよ」":[1692],"「わかった！」":[1692],"「アタイがあまりにも天才だから":[1692],"「嫉妬してるんでしょ？」":[1692],"「ほんと、しょうがないわねぇ」":[1692],"「せっかくだからアタイの天才の秘訣を」":[1692],"「ちょっとだけ教えてあげてもいいわよ」":[1692],"「ばーかばーか！」":[1692],"「もうバカでいいわよ、知らない！」":[1692],"「あなただけ見つめてる」":[1693],"「お帰り」の言葉":[1693],"「行こうぜ":[3614],"「夢」とは違う":[3616],"「生活リズム":[3616],"「夜更かしお寝坊":[3616],"「安心と安全を":[3616],"「ありのまま」なんて":[3618],"「ぼやけたままのフォーカスじゃ":[3619],"「作者の気持ちを答えなさい」":[3622],"「わかるわかる、同じ気持ちさ」":[3622],"「進めよ」と":[3622],"「いいや":[3623]}