{"あらゆる":[1717],"あたいの":[1717],"あたいは":[1717,1718],"あなたと":[1718],"あたいが":[1718],"あたりは":[1718],"あなた言うけど":[1718],"あなたと過ごした":[1718],"あんｄ":[1778],"あずけてplease":[3672],"あのバンドの歌がわたしには":[3675],"あのバンドの歌が誰かにはギプスで":[3675],"あのバンド":[3675],"あのね、その後が言えなかった日も":[3676],"あいむあらいぶなういえ":[3676],"あのね、その後が言えた日の笑顔も":[3676],"あのさ":[3677],"あるからいいんだよ":[3678],"あぁカラカラ騒ぐ思考飛ばして":[3679],"あぁ傘もないや嫌":[3680],"ああ":[3680,3682],"あまりに眩しい":[3681],"ああ嫌だ":[3682],"あぁ":[3683],"あの丘を越えたその先は":[3686],"あの日に全部捨ててる":[3688],"あなただけが":[3689],"あーいった感じも":[3690],"あーゆうのアリかな":[3690]}