{"そう知らない？":[127],"それだけ":[127],"それだけ？":[127],"それは":[1702],"そんなつぼあるわけない":[1702],"そっと":[1703],"そんな夜":[3626],"そうだろう":[3626],"それでもうしろ振り向かずに進むよ":[3629],"そう":[3630],"その手で":[3632],"そんなに光るなよ":[3632],"それだけで":[3633],"それでも何か":[3635],"それでも知ってるから":[3636],"それもあるよな":[3638],"それどころか":[3638],"そんな僕に術はないよな":[3638],"それさえもわからないんだ":[3638],"そんな夜を温めるように歌うんだ":[3638],"それでいい":[3639],"それでも":[3640],"それが":[3640],"その日を待ってる":[3640],"そばに":[3640],"そっとふれるもの":[3641],"その背中には":[3641],"そら":[3641],"その夢に目覚めたとき":[3641],"そうキミを待つのは":[3642],"そんじゃ、いっか、ホントの私はシークレットモードで営業スイッチオン":[3642],"そう、いつも通りの毎日に":[3642],"そこ":[3643]}